argparse2typer/__init__.py
argparse2typer/argparse2typer.py
argparse2typer-0.0.2.dist-info/METADATA
argparse2typer-0.0.2.dist-info/WHEEL
argparse2typer-0.0.2.dist-info/licenses/LICENSE
argparse2typer-0.0.2.dist-info/RECORD
