Metadata-Version: 2.1
Name: argparse2typer
Version: 0.0.2
Summary: Convert Python's default argparse into typer CLI
Project-URL: Homepage, https://github.com/bomcon123456/argparse2typer
Project-URL: Bug Tracker, https://github.com/pypa/argparse2typer/issues
Author-email: termanteus <termanteus@gmail.com>
License-File: LICENSE
Classifier: License :: OSI Approved :: MIT License
Classifier: Operating System :: OS Independent
Classifier: Programming Language :: Python :: 3
Requires-Python: >=3.7
Requires-Dist: num2words
